recaptcha_solver_google/__init__.py
recaptcha_solver_google/solver.py
recaptcha_solver_google-0.1.7.dist-info/METADATA
recaptcha_solver_google-0.1.7.dist-info/WHEEL
recaptcha_solver_google-0.1.7.dist-info/top_level.txt
recaptcha_solver_google-0.1.7.dist-info/RECORD
