Metadata-Version: 2.1
Name: recaptcha_solver_google
Version: 0.1.7
Summary: A package to solve Google reCAPTCHA using Selenium.
Home-page: https://github.com/yourusername/recaptcha_solver_google
Author: Mohd Shakir
Classifier: Programming Language :: Python :: 3
Classifier: Operating System :: OS Independent
Requires-Python: >=3.6
Requires-Dist: selenium
Requires-Dist: pydub
Requires-Dist: SpeechRecognition
Requires-Dist: urllib3
Requires-Dist: platform
Requires-Dist: zipfile
Requires-Dist: tarfile
